odoo/addons/document_page_reference/README.rst
odoo/addons/document_page_reference/__init__.py
odoo/addons/document_page_reference/__manifest__.py
odoo/addons/document_page_reference/i18n/document_page_reference.pot
odoo/addons/document_page_reference/i18n/fr.po
odoo/addons/document_page_reference/i18n/pt_BR.po
odoo/addons/document_page_reference/models/__init__.py
odoo/addons/document_page_reference/models/document_page.py
odoo/addons/document_page_reference/readme/CONTRIBUTORS.rst
odoo/addons/document_page_reference/readme/DESCRIPTION.rst
odoo/addons/document_page_reference/readme/USAGE.rst
odoo/addons/document_page_reference/static/description/icon.png
odoo/addons/document_page_reference/static/description/index.html
odoo/addons/document_page_reference/static/src/js/editor.js
odoo/addons/document_page_reference/tests/__init__.py
odoo/addons/document_page_reference/tests/test_document_reference.py
odoo/addons/document_page_reference/views/assets.xml
odoo/addons/document_page_reference/views/document_page.xml
odoo/addons/document_page_reference/views/report_document_page.xml
odoo12_addon_document_page_reference-12.0.1.0.2.dist-info/METADATA
odoo12_addon_document_page_reference-12.0.1.0.2.dist-info/WHEEL
odoo12_addon_document_page_reference-12.0.1.0.2.dist-info/top_level.txt
odoo12_addon_document_page_reference-12.0.1.0.2.dist-info/RECORD
